{
  "gitSyncId": "6720a67ba54dd05886d659fc_427cab66-1bbb-4fba-b5d7-85999f06a3c3",
  "id": "ProfilePage_educationAndWorkexJsObject.resetwidget",
  "pluginId": "js-plugin",
  "pluginType": "JS",
  "unpublishedAction": {
    "actionConfiguration": {
      "encodeParamsToggle": true,
      "jsArguments": [],
      "paginationType": "NONE",
      "timeoutInMillisecond": 10000
    },
    "collectionId": "ProfilePage_educationAndWorkexJsObject",
    "confirmBeforeExecute": false,
    "datasource": {
      "isAutoGenerated": false,
      "name": "UNUSED_DATASOURCE",
      "pluginId": "js-plugin"
    },
    "dynamicBindingPathList": [
      {
        "key": "body"
      }
    ],
    "executeOnLoad": false,
    "fullyQualifiedName": "educationAndWorkexJsObject.resetwidget",
    "name": "resetwidget",
    "pageId": "ProfilePage",
    "userSetOnLoad": false
  }
}